Metadata-Version: 2.1
Name: mypackcalci
Version: 0.0.1
Summary: this is a trial package used for calculation.
Home-page: UNKNOWN
Author: Vindhya Mudgal
Author-email: vindhyamudgal@gmail.com
License: MIT
Platform: UNKNOWN
License-File: Licence.txt
